octoanalytics/__init__.py
octoanalytics/cdc_profiler.py
octoanalytics/core.py
octoanalytics/data_extractor.py
octoanalytics/forecast.py
octoanalytics/risk_premium.py
octoanalytics/pricing_backend/__init__.py
octoanalytics/pricing_backend/example_read_load_curve.py
octoanalytics/pricing_backend/config/__init__.py
octoanalytics/pricing_backend/config/loader.py
octoanalytics/pricing_backend/src/__init__.py
octoanalytics/pricing_backend/src/models/__init__.py
octoanalytics/pricing_backend/src/models/contracts.py
octoanalytics/pricing_backend/src/processing/__init__.py
octoanalytics/pricing_backend/src/processing/load_curve_processor.py
octoanalytics/pricing_backend/src/utils/__init__.py
octoanalytics/pricing_backend/src/utils/date_utils.py
octoanalytics/pricing_backend/src/utils/file_utils.py
octoanalytics-0.3.6.dist-info/licenses/LICENSE
octoanalytics-0.3.6.dist-info/METADATA
octoanalytics-0.3.6.dist-info/WHEEL
octoanalytics-0.3.6.dist-info/top_level.txt
octoanalytics-0.3.6.dist-info/RECORD
