Metadata-Version: 2.4
Name: octoanalytics
Version: 0.3.6
Summary: Quantitative analysis for power markets
Author: Jean Bertin, Thomas Maaza
Author-email: <jean.bertin@octopusenergy.fr>, <thomas.maaza@octoenergy.com>
Keywords: python,quantitative,risk,power,quant,octopusenergy
Classifier: Development Status :: 1 - Planning
Classifier: Intended Audience :: Developers
Classifier: Programming Language :: Python :: 3
Classifier: Operating System :: Unix
Classifier: Operating System :: MacOS :: MacOS X
Classifier: Operating System :: Microsoft :: Windows
License-File: LICENSE
Requires-Dist: pandas
Requires-Dist: numpy
Requires-Dist: scikit-learn
Requires-Dist: holidays
Requires-Dist: matplotlib
Requires-Dist: requests
Requires-Dist: tqdm
Requires-Dist: plotly
Requires-Dist: tentaclio
Requires-Dist: python-dotenv
Requires-Dist: python-dateutil
Requires-Dist: databricks-sql-connector
Requires-Dist: yaspin
Requires-Dist: urllib3
Dynamic: author
Dynamic: author-email
Dynamic: classifier
Dynamic: description
Dynamic: description-content-type
Dynamic: keywords
Dynamic: license-file
Dynamic: requires-dist
Dynamic: summary
